py_bipartite_matching/__init__.py
py_bipartite_matching/biparite_sample.py
py_bipartite_matching/brute_force_bipartite_matching.py
py_bipartite_matching/graphs_utils.py
py_bipartite_matching/py_bipartite_matching.py
py_bipartite_matching-0.2.0.dist-info/AUTHORS.rst
py_bipartite_matching-0.2.0.dist-info/LICENSE
py_bipartite_matching-0.2.0.dist-info/METADATA
py_bipartite_matching-0.2.0.dist-info/WHEEL
py_bipartite_matching-0.2.0.dist-info/top_level.txt
py_bipartite_matching-0.2.0.dist-info/RECORD
