Metadata-Version: 2.1
Name: py-bipartite-matching
Version: 0.2.0
Summary: Py Bipartite Matching contains bipartite graphs matching algorithms.
Home-page: https://github.com/FranciscoMoretti/py_bipartite_matching
Author: Francisco Moretti
Author-email: franciscoemoretti@gmail.com
License: MIT license
Keywords: py_bipartite_matching
Platform: UNKNOWN
Classifier: Development Status :: 2 - Pre-Alpha
Classifier: Intended Audience :: Developers
Classifier: License :: OSI Approved :: MIT License
Classifier: Natural Language :: English
Classifier: Programming Language :: Python :: 3
Classifier: Programming Language :: Python :: 3.7
Classifier: Programming Language :: Python :: 3.8
Classifier: Programming Language :: Python :: 3.9
Requires-Python: >=3.7
